MANIFEST.in
README.rst
setup.py
predata/__init__.py
predata/client.py
predata/clients/__init__.py
predata/clients/analysis_client.py
predata/clients/data_client.py
predata/clients/generic_client.py
predata/clients/signal_client.py
predata/clients/user_client.py
predata/config/__init__.py
predata/config/constants.py
predata/config/exceptions.py
predata/config/logger.py
predata_api_client.egg-info/PKG-INFO
predata_api_client.egg-info/SOURCES.txt
predata_api_client.egg-info/dependency_links.txt
predata_api_client.egg-info/requires.txt
predata_api_client.egg-info/top_level.txt