Metadata-Version: 1.1
Name: predata-api-client
Version: 0.9.0
Summary: Predata Python API Client
Home-page: http://www.predata.com
Author: predata
Author-email: dev@predata.com
License: UNKNOWN
Platform: UNKNOWN
Classifier: Intended Audience :: Developers
Classifier: License :: OSI Approved :: MIT License
Classifier: Operating System :: OS Independent
Classifier: Programming Language :: Python
